codekite/__init__.py
codekite/cli.py
codekite/code_searcher.py
codekite/context_extractor.py
codekite/dependency_analyzer.py
codekite/docstring_indexer.py
codekite/llm_context.py
codekite/repo_mapper.py
codekite/repository.py
codekite/summaries.py
codekite/tree_sitter_symbol_extractor.py
codekite/vector_searcher.py
codekite/api/__init__.py
codekite/api/app.py
codekite-0.1.7.dist-info/licenses/LICENSE
codekite-0.1.7.dist-info/METADATA
codekite-0.1.7.dist-info/WHEEL
codekite-0.1.7.dist-info/entry_points.txt
codekite-0.1.7.dist-info/top_level.txt
codekite-0.1.7.dist-info/RECORD
