Metadata-Version: 2.4
Name: codekite
Version: 0.1.7
Summary: A modular toolkit for LLM powered codebase understanding.
Author-email: Shane Holloman <shaneholloman@gmail.com>
License: MIT
Project-URL: Homepage, https://github.com/shaneholloman/codekite
Requires-Python: >=3.10
License-File: LICENSE
Requires-Dist: tree-sitter-language-pack>=0.7.2
Requires-Dist: pathspec>=0.11.1
Requires-Dist: pytest>=8.3.5
Requires-Dist: numpy>=1.25
Requires-Dist: chromadb>=0.5.25
Requires-Dist: sentence-transformers>=2.2.0
Requires-Dist: fastapi>=0.100
Requires-Dist: uvicorn[standard]>=0.20
Requires-Dist: typer>=0.9
Requires-Dist: openai>=1.0.0
Requires-Dist: tiktoken>=0.4.0
Requires-Dist: anthropic>=0.20.0
Requires-Dist: google-genai>=1.14.0
Requires-Dist: mypy
Requires-Dist: ruff
Requires-Dist: black
Dynamic: license-file
